setup.py
YourMother/__init__.py
YourMother.egg-info/PKG-INFO
YourMother.egg-info/SOURCES.txt
YourMother.egg-info/dependency_links.txt
YourMother.egg-info/top_level.txt